{
  "properties": [
    {
      "name": "spring.jackson.constructor-detector",
      "defaultValue": "default"
    },
    {
      "name": "spring.jackson.datatype.enum",
      "description": "Jackson on/off features for enums."
    },
    {
      "name": "spring.jackson.generator",
      "deprecation": {
        "level": "error",
        "reason": "Partially replaced by 'spring.jackson.json.read'."
      }
    },
    {
      "name": "spring.jackson.joda-date-time-format",
      "type": "java.lang.String",
      "description": "Joda date time format string. If not configured, \"date-format\" is used as a fallback if it is configured with a format string.",
      "deprecation": {
        "level": "error"
      }
    },
    {
      "name": "spring.jackson.parser",
      "deprecation": {
        "level": "error",
        "reason": "Partially replaced by 'spring.jackson.json.write'."
      }
    },
    {
      "name": "spring.jackson.read",
      "type": "java.util.Map<tools.jackson.core.json.JsonReadFeature,java.lang.Boolean>",
      "description": "Jackson on/off token reader features that are specific to JSON.",
      "sourceType": "org.springframework.boot.jackson.autoconfigure.JacksonProperties",
      "deprecation": {
        "level": "error",
        "replacement": "spring.jackson.json.read"
      }
    },
    {
      "name": "spring.jackson.write",
      "type": "java.util.Map<tools.jackson.core.json.JsonWriteFeature,java.lang.Boolean>",
      "description": "Jackson on/off token writer features that are specific to JSON.",
      "sourceType": "org.springframework.boot.jackson.autoconfigure.JacksonProperties",
      "deprecation": {
        "level": "error",
        "replacement": "spring.jackson.json.write"
      }
    }
  ]
}
